mimic/__init__.py
mimic/pretrained_model_factory.py
mimic/text_generator.py
mimic/text_generator_factory.py
mimic/text_translator.py
mimic/util.py
mimic/model/__init__.py
mimic/model/gru_model.py
mimic/model/lstm_model.py
mimic/model/markov_chain_model.py
mimic/model/model.py
mimic/model/translation_model.py
mimic/tests/__init__.py
mimic/tests/test_text_generator.py
mimic/tests/test_text_generator_factory.py
mimic/tests/test_util.py
mimic_text-0.0.2.dist-info/LICENSE
mimic_text-0.0.2.dist-info/METADATA
mimic_text-0.0.2.dist-info/WHEEL
mimic_text-0.0.2.dist-info/top_level.txt
mimic_text-0.0.2.dist-info/RECORD
