Metadata-Version: 2.1
Name: mimic-text
Version: 0.0.2
Summary: ML-powered Text Generation Library
Home-page: https://github.com/ubclaunchpad/mimic
Author: ubclaunchpad
Author-email: 
License: MIT
Platform: UNKNOWN
